src/__init__.py
src/__main__.py
src/tardys3_generator.py
tardys3_generator-0.1.1.dist-info/licenses/LICENSE.txt
tardys3_generator-0.1.1.dist-info/METADATA
tardys3_generator-0.1.1.dist-info/WHEEL
tardys3_generator-0.1.1.dist-info/entry_points.txt
tardys3_generator-0.1.1.dist-info/top_level.txt
tardys3_generator-0.1.1.dist-info/RECORD
