Metadata-Version: 2.4
Name: tardys3-generator
Version: 0.1.1
Summary: A TARDyS3 reservation file generator and validator for CBRS P-DPAs.
Home-page: https://github.com/yourusername/tardys3-generator
Author: Masheenist
Author-email: syll7976@colorado.edu
Classifier: Programming Language :: Python :: 3
Classifier: License :: OSI Approved :: BSD License
Classifier: Operating System :: OS Independent
Requires-Python: >=3.7
License-File: LICENSE.txt
Requires-Dist: jsonschema>=4.0.0
Requires-Dist: tkcalendar>=1.6.1
Dynamic: author
Dynamic: author-email
Dynamic: classifier
Dynamic: description
Dynamic: description-content-type
Dynamic: home-page
Dynamic: license-file
Dynamic: requires-dist
Dynamic: requires-python
Dynamic: summary
